model_solver/__init__.py
model_solver/model_solver.py
model_solver/py.typed
ssb_model_solver-1.4.2.dist-info/LICENSE
ssb_model_solver-1.4.2.dist-info/METADATA
ssb_model_solver-1.4.2.dist-info/WHEEL
ssb_model_solver-1.4.2.dist-info/RECORD
