Metadata-Version: 2.3
Name: ssb-model-solver
Version: 1.4.2
Summary: Class to define, block analyse and solve dynamic and algebraic models numerically
License: MIT
Author: Benedikt Goodman
Author-email: benedikt.goodman@ssb.no
Requires-Python: >=3.10,<4.0
Classifier: Development Status :: 4 - Beta
Classifier: License :: OSI Approved :: MIT License
Classifier: Programming Language :: Python :: 3
Classifier: Programming Language :: Python :: 3.10
Classifier: Programming Language :: Python :: 3.11
Classifier: Programming Language :: Python :: 3.12
Classifier: Programming Language :: Python :: 3.13
Requires-Dist: matplotlib (>=3.7.1)
Requires-Dist: networkx (>=3.3)
Requires-Dist: numba (>=0.57.0)
Requires-Dist: numpy (>=1.26)
Requires-Dist: pandas (>=2.0)
Requires-Dist: symengine (>=0.9.2)
Project-URL: Changelog, https://github.com/statisticsnorway/ssb-model-solver/releases
Project-URL: Documentation, https://statisticsnorway.github.io/ssb-model-solver
Project-URL: Homepage, https://github.com/statisticsnorway/ssb-model-solver
Project-URL: Repository, https://github.com/statisticsnorway/ssb-model-solver
